ngsfetch/__init__.py
ngsfetch/download.py
ngsfetch/ffq.py
ngsfetch/general.py
ngsfetch/main.py
ngsfetch/md5sum.py
ngsfetch-0.1.1.dist-info/licenses/LICENSE
ngsfetch-0.1.1.dist-info/METADATA
ngsfetch-0.1.1.dist-info/WHEEL
ngsfetch-0.1.1.dist-info/entry_points.txt
ngsfetch-0.1.1.dist-info/top_level.txt
ngsfetch-0.1.1.dist-info/RECORD
