Metadata-Version: 2.4
Name: ngsfetch
Version: 0.1.1
Summary: Fast metadata and fastq retrieval with ffq and aria2c
Author-email: Naoto Kubota <the.owner.of.the.dream123@gmail.com>
License: MIT
Project-URL: Homepage, https://github.com/NaotoKubota/ngsfetch
Requires-Python: >=3.9
License-File: LICENSE
Requires-Dist: ffq>=0.3.1
Requires-Dist: aria2>=0.0.1b0
Dynamic: license-file
